dennisnotojr_weather/main.py
dennisnotojr_weather/server.py
dennisnotojr_weather-0.1.2.dist-info/METADATA
dennisnotojr_weather-0.1.2.dist-info/WHEEL
dennisnotojr_weather-0.1.2.dist-info/entry_points.txt
dennisnotojr_weather-0.1.2.dist-info/top_level.txt
dennisnotojr_weather-0.1.2.dist-info/RECORD
