Metadata-Version: 2.4
Name: dennisnotojr-weather
Version: 0.1.2
Summary: MCP server to get weather forecast from national weather service
Author-email: dennisnotojr <dennisnoto@gmail.com>
Requires-Python: >=3.12
Requires-Dist: httpx>=0.28.1
Requires-Dist: mcp[cli]>=1.10.1
